tvb/__init__.py
tvb/adapters/__init__.py
tvb/adapters/analyzers/__init__.py
tvb/adapters/analyzers/bct_adapters.py
tvb/adapters/analyzers/bct_centrality_adapters.py
tvb/adapters/analyzers/bct_clustering_adapters.py
tvb/adapters/analyzers/bct_degree_adapters.py
tvb/adapters/analyzers/cross_correlation_adapter.py
tvb/adapters/analyzers/fcd_adapter.py
tvb/adapters/analyzers/fmri_balloon_adapter.py
tvb/adapters/analyzers/fourier_adapter.py
tvb/adapters/analyzers/ica_adapter.py
tvb/adapters/analyzers/metrics_group_timeseries.py
tvb/adapters/analyzers/node_coherence_adapter.py
tvb/adapters/analyzers/node_complex_coherence_adapter.py
tvb/adapters/analyzers/node_covariance_adapter.py
tvb/adapters/analyzers/pca_adapter.py
tvb/adapters/analyzers/wavelet_adapter.py
tvb/adapters/creators/__init__.py
tvb/adapters/creators/allen_creator.py
tvb/adapters/creators/connectivity_creator.py
tvb/adapters/creators/local_connectivity_creator.py
tvb/adapters/creators/siibra_base.py
tvb/adapters/creators/siibra_creator.py
tvb/adapters/creators/stimulus_creator.py
tvb/adapters/datatypes/__init__.py
tvb/adapters/datatypes/db/__init__.py
tvb/adapters/datatypes/db/annotation.py
tvb/adapters/datatypes/db/connectivity.py
tvb/adapters/datatypes/db/fcd.py
tvb/adapters/datatypes/db/graph.py
tvb/adapters/datatypes/db/local_connectivity.py
tvb/adapters/datatypes/db/mapped_value.py
tvb/adapters/datatypes/db/mode_decompositions.py
tvb/adapters/datatypes/db/patterns.py
tvb/adapters/datatypes/db/projections.py
tvb/adapters/datatypes/db/region_mapping.py
tvb/adapters/datatypes/db/sensors.py
tvb/adapters/datatypes/db/simulation_history.py
tvb/adapters/datatypes/db/spectral.py
tvb/adapters/datatypes/db/structural.py
tvb/adapters/datatypes/db/surface.py
tvb/adapters/datatypes/db/temporal_correlations.py
tvb/adapters/datatypes/db/time_series.py
tvb/adapters/datatypes/db/tracts.py
tvb/adapters/datatypes/db/volume.py
tvb/adapters/datatypes/db/removers/remover_connectivity.py
tvb_framework-2.9.1.dist-info/AUTHORS
tvb_framework-2.9.1.dist-info/LICENSE
tvb_framework-2.9.1.dist-info/METADATA
tvb_framework-2.9.1.dist-info/WHEEL
tvb_framework-2.9.1.dist-info/top_level.txt
tvb_framework-2.9.1.dist-info/RECORD
