Metadata-Version: 2.1
Name: tvb-framework
Version: 2.9.1
Summary: A package for performing whole brain simulations
Home-page: https://www.thevirtualbrain.org
Download-URL: https://github.com/the-virtual-brain/tvb-root
Author: Mihai Andrei, Lia Domide, Stuart Knock, Bogdan Neacsa, Paula Prodan, Paula Sansz Leon, Marmaduke Woodman
Author-email: tvb.admin@thevirtualbrain.org
License: GPL-3.0-or-later
Keywords: tvb brain simulator neuroscience human animal neuronal dynamics models delay
Classifier: Development Status :: 6 - Mature
Classifier: Intended Audience :: Science/Research
Classifier: License :: OSI Approved :: GNU General Public License v3 or later (GPLv3+)
Classifier: Programming Language :: Python :: 3
License-File: LICENSE
License-File: AUTHORS
Requires-Dist: alembic
Requires-Dist: bctpy
Requires-Dist: cherrypy
Requires-Dist: docutils
Requires-Dist: flask
Requires-Dist: flask-restx
Requires-Dist: formencode
Requires-Dist: gevent
Requires-Dist: h5py
Requires-Dist: Jinja2
Requires-Dist: matplotlib
Requires-Dist: nibabel
Requires-Dist: numpy <2.0
Requires-Dist: pandas
Requires-Dist: Pillow
Requires-Dist: psutil
Requires-Dist: python-keycloak
Requires-Dist: requests
Requires-Dist: requests-toolbelt >=0.10
Requires-Dist: scikit-learn
Requires-Dist: scipy
Requires-Dist: siibra
Requires-Dist: simplejson
Requires-Dist: six
Requires-Dist: sqlalchemy
Requires-Dist: tvb-data
Requires-Dist: tvb-gdist
Requires-Dist: tvb-library
Requires-Dist: tvb-storage
Requires-Dist: werkzeug
Provides-Extra: extra
Requires-Dist: allensdk ; extra == 'extra'
Provides-Extra: hpc
Requires-Dist: pyunicore ; extra == 'hpc'
Requires-Dist: elasticsearch ; extra == 'hpc'
Provides-Extra: postgres
Requires-Dist: psycopg2 ; extra == 'postgres'
Provides-Extra: test
Requires-Dist: pytest ; extra == 'test'
Requires-Dist: pytest-benchmark ; extra == 'test'
Requires-Dist: pytest-mock ; extra == 'test'
Requires-Dist: BeautifulSoup4 ; extra == 'test'
